mtlibs/.dockerignore
mtlibs/.gitignore
mtlibs/Dockerfile
mtlibs/README.md
mtlibs/bin/dev_init
mtlibs/bin/publish
mtlibs/compose.yml
mtlibs/mtlibs2/SSH.py
mtlibs/mtlibs2/__init__.py
mtlibs/mtlibs2/amplifyHelper.py
mtlibs/mtlibs2/auth0_utils.py
mtlibs/mtlibs2/aws/__init__.py
mtlibs/mtlibs2/aws/ddb_helper.py
mtlibs/mtlibs2/aws/s3_helper copy.py--
mtlibs/mtlibs2/aws/s3_helper.py
mtlibs/mtlibs2/aws/s3_imageresize.py
mtlibs/mtlibs2/az/demo1222.py--
mtlibs/mtlibs2/az/webdeploy.py--
mtlibs/mtlibs2/az/webdeploy2.py--
mtlibs/mtlibs2/cli/__init__.py
mtlibs/mtlibs2/cli/dc.py
mtlibs/mtlibs2/cli/dockerdev.py
mtlibs/mtlibs2/cli/gitup.py
mtlibs/mtlibs2/cli/mtbuild.py
mtlibs/mtlibs2/cli/mtbundler.py
mtlibs/mtlibs2/cli/mtdp.py
mtlibs/mtlibs2/cli/mtgp.py
mtlibs/mtlibs2/cli/mtngrok.py
mtlibs/mtlibs2/cli/mtproxy.py--
mtlibs/mtlibs2/cli/mtpub.py
mtlibs/mtlibs2/cli/mtwpdev.py
mtlibs/mtlibs2/cli/phpfpm.py
mtlibs/mtlibs2/cli/sub_commands/__init__.py
mtlibs/mtlibs2/cli/sub_commands/azure_rancher_group.py
mtlibs/mtlibs2/cli/sub_commands/build.py
mtlibs/mtlibs2/cli/sub_commands/default.py
mtlibs/mtlibs2/cli/sub_commands/demoflask.py
mtlibs/mtlibs2/cli/sub_commands/dev.py
mtlibs/mtlibs2/cli/sub_commands/devserver.py
mtlibs/mtlibs2/cli/sub_commands/port.py
mtlibs/mtlibs2/cli/sub_commands/proxy.py
mtlibs/mtlibs2/cli/sub_commands/simplehttp.py
mtlibs/mtlibs2/cli/sub_commands/sshd.py
mtlibs/mtlibs2/cli/sub_commands/version.py
mtlibs/mtlibs2/cognito_util.py
mtlibs/mtlibs2/config.py
mtlibs/mtlibs2/container_config.py
mtlibs/mtlibs2/data/clash/config copy.yaml
mtlibs/mtlibs2/data/clash/config-tproxy copy.yml--
mtlibs/mtlibs2/data/clash/config-tproxy.yml--
mtlibs/mtlibs2/data/clash/config.yaml
mtlibs/mtlibs2/data/clash/config_direct.yaml
mtlibs/mtlibs2/data/clash/config_local.yaml
mtlibs/mtlibs2/data/mitmproxy/command_history
mtlibs/mtlibs2/data/mitmproxy/mitmproxy-ca-cert.cer
mtlibs/mtlibs2/data/mitmproxy/mitmproxy-ca-cert.p12
mtlibs/mtlibs2/data/mitmproxy/mitmproxy-ca-cert.pem
mtworker-0.1.13.dist-info/WHEEL
mtworker-0.1.13.dist-info/METADATA
mtworker-0.1.13.dist-info/RECORD
