Metadata-Version: 2.1
Name: mtworker
Version: 0.1.13
Summary: 
Author: a
Author-email: a@a.com
Requires-Python: >=3.10,<4.0
Classifier: Programming Language :: Python :: 3
Classifier: Programming Language :: Python :: 3.10
Classifier: Programming Language :: Python :: 3.11
Requires-Dist: celery[redis] (>=5.2.7,<6.0.0)
Requires-Dist: httpx (>=0.23.3,<0.24.0)
Requires-Dist: playwright (>=1.29.1,<2.0.0)
Requires-Dist: requests (>=2.28.2,<3.0.0)
Requires-Dist: typer[all] (>=0.7.0,<0.8.0)
